DbUnify/__init__.py
DbUnify/SQLite3/Cache.py
DbUnify/SQLite3/QueryBuilder.py
DbUnify/SQLite3/__init__.py
DbUnify/SQLite3/aio/Cache.py
DbUnify/SQLite3/aio/__init__.py
DbUnify/SQLite3/aio/Exporter/Exporter.py
DbUnify/SQLite3/aio/Exporter/__init__.py
DbUnify/SQLite3/aio/Manager/Manager.py
DbUnify/SQLite3/aio/Manager/__init__.py
DbUnify/SQLite3/aio/ORM/Field.py
DbUnify/SQLite3/aio/ORM/Model.py
DbUnify/SQLite3/aio/ORM/ModelMeta.py
DbUnify/SQLite3/aio/ORM/ORMException.py
DbUnify/SQLite3/aio/ORM/ORMManager.py
DbUnify/SQLite3/aio/ORM/Types.py
DbUnify/SQLite3/aio/ORM/__init__.py
DbUnify/SQLite3/aio/Raw/Raw.py
DbUnify/SQLite3/aio/Raw/__init__.py
DbUnify/SQLite3/data/Rules.py
DbUnify/SQLite3/data/Type.py
DbUnify/SQLite3/data/__init__.py
DbUnify/SQLite3/sync/__init__.py
DbUnify/SQLite3/sync/Exporter/Exporter.py
DbUnify/SQLite3/sync/Exporter/ExporterException.py
DbUnify/SQLite3/sync/Exporter/__init__.py
DbUnify/SQLite3/sync/Live/LiveEvents.py
DbUnify/SQLite3/sync/Live/LiveException.py
DbUnify/SQLite3/sync/Live/LiveManager.py
DbUnify/SQLite3/sync/Live/__init__.py
DbUnify/SQLite3/sync/Live/obj.py
DbUnify/SQLite3/sync/Manager/Manager.py
DbUnify/SQLite3/sync/Manager/__init__.py
DbUnify/SQLite3/sync/ORM/Field.py
DbUnify/SQLite3/sync/ORM/Model.py
DbUnify/SQLite3/sync/ORM/ModelMeta.py
DbUnify/SQLite3/sync/ORM/ORMException.py
DbUnify/SQLite3/sync/ORM/ORMManager.py
DbUnify/SQLite3/sync/ORM/Types.py
DbUnify/SQLite3/sync/ORM/__init__.py
DbUnify/SQLite3/sync/Raw/Raw.py
DbUnify/SQLite3/sync/Raw/__init__.py
DbUnify-2.1.2.dist-info/LICENSE
DbUnify-2.1.2.dist-info/METADATA
DbUnify-2.1.2.dist-info/WHEEL
DbUnify-2.1.2.dist-info/top_level.txt
DbUnify-2.1.2.dist-info/RECORD
