Metadata-Version: 2.1
Name: DbUnify
Version: 2.1.2
Summary: DbUnify (Database Management) is a versatile Python library that simplifies database connectivity and management using SQLite.
Home-page: https://github.com/Sepehr267/DbUnify
Author: Sepehr0Day
Author-email: sphrz2324@gmail.com
License: MIT
Project-URL: Documentation, https://DbUnify.readthedocs.io/
Project-URL: Source, https://github.com/Sepehr267/DbUnify/DbUnify
Project-URL: Bug Reports, https://github.com/Sepehr267/DbUnify/issues
Keywords: DbUnify database sqlite3 sql SQL sepehr0day Management
Classifier: Development Status :: 5 - Production/Stable
Classifier: Intended Audience :: Developers
Classifier: License :: OSI Approved :: MIT License
Classifier: Programming Language :: Python :: 3
Classifier: Programming Language :: Python :: 3.7
Classifier: Programming Language :: Python :: 3.8
Classifier: Programming Language :: Python :: 3.9
Classifier: Programming Language :: Python :: 3.10
Classifier: Operating System :: OS Independent
Requires-Python: >=3.7
License-File: LICENSE
Requires-Dist: matplotlib
Requires-Dist: aiosqlite
Requires-Dist: asyncio
